sqlalchemy_auth_hooks/__init__.py
sqlalchemy_auth_hooks/auth_handler.py
sqlalchemy_auth_hooks/authorization.py
sqlalchemy_auth_hooks/events.py
sqlalchemy_auth_hooks/hooks.py
sqlalchemy_auth_hooks/oso/__init__.py
sqlalchemy_auth_hooks/oso/oso_handler.py
sqlalchemy_auth_hooks/oso/sqlalchemy_oso/NOTICE
sqlalchemy_auth_hooks/oso/sqlalchemy_oso/__init__.py
sqlalchemy_auth_hooks/oso/sqlalchemy_oso/auth.py
sqlalchemy_auth_hooks/oso/sqlalchemy_oso/compat.py
sqlalchemy_auth_hooks/oso/sqlalchemy_oso/partial.py
sqlalchemy_auth_hooks/oso/sqlalchemy_oso/preprocess.py
sqlalchemy_auth_hooks/post_auth_handler.py
sqlalchemy_auth_hooks/py.typed
sqlalchemy_auth_hooks/references.py
sqlalchemy_auth_hooks/session.py
sqlalchemy_auth_hooks/utils.py
sqlalchemy_auth_hooks-0.0.2.dist-info/LICENSE
sqlalchemy_auth_hooks-0.0.2.dist-info/METADATA
sqlalchemy_auth_hooks-0.0.2.dist-info/WHEEL
sqlalchemy_auth_hooks-0.0.2.dist-info/RECORD
